ztfcosmo/__init__.py
ztfcosmo/io.py
ztfcosmo/lightcurve.py
ztfcosmo/spectrum.py
ztfcosmo/utils.py
ztfcosmo-1.3.3.dist-info/LICENSE
ztfcosmo-1.3.3.dist-info/METADATA
ztfcosmo-1.3.3.dist-info/WHEEL
ztfcosmo-1.3.3.dist-info/top_level.txt
ztfcosmo-1.3.3.dist-info/RECORD
